README.md
manta/.DS_Store
manta/__init__.py
manta/banner.py
manta/cli/__init__.py
manta/cli/typer_cli.py
manta/color_theme/__init__.py
manta/color_theme/carolus/__init__.py
manta/color_theme/carolus/corolus_theme.py
manta/color_theme/catppucin/__init__.py
manta/color_theme/catppucin/catppuccin_frappe.py
manta/color_theme/catppucin/catppuccin_latte.py
manta/color_theme/catppucin/catppuccin_macchiato.py
manta/color_theme/catppucin/catppuccin_mocha.py
manta/color_theme/catppucin/catppuccin_theme_ABC.py
manta/color_theme/color_theme_ABC.py
manta/color_theme/rwth/__init__.py
manta/color_theme/rwth/rwth_theme.py
manta/color_theme/tokyo_night/__init__.py
manta/color_theme/tokyo_night/tokyo_night.py
manta/color_theme/tokyo_night/tokyo_night_ABC.py
manta/color_theme/tokyo_night/tokyo_night_day.py
manta/color_theme/tokyo_night/tokyo_night_moon.py
manta/color_theme/tokyo_night/tokyo_night_storm.py
manta/components/__init__.py
manta/components/axes_utils.py
manta/components/gantt_utils.py
manta/components/go_board_utils.py
manta/components/iqs_utils.py
manta/components/nerdfont_icons.py
manta/components/neural_networks_utils.py
manta/components/qr_code_utils.py
manta/components/rectangle_utils.py
manta/components/shapes.py
manta/components/text.py
manta/components/uml_utils.py
manta/doc_example.py
manta/docbuild/__init__.py
manta/docbuild/image_path_utils.py
manta/docbuild/manta_directive.py
manta/examples/.DS_Store
manta/examples/__init__.py
manta/examples/agenda/__init__.py
manta/examples/agenda/example_agenda_fade_in_all_at_once.py
manta/examples/agenda/example_agenda_fade_in_step_by_step.py
manta/examples/axes/__init__.py
manta/examples/axes/axes2.py
manta/examples/axes/axes_example.py
manta/examples/axes/slides.html
manta/examples/expose/.DS_Store
manta/examples/expose/__init__.py
manta/examples/expose/aa_intro_slide.py
manta/examples/expose/ab_cv_slide.py
manta/examples/expose/ac_agenda.py
manta/examples/expose/ad_motivation.py
manta/examples/expose/ae_scientific_goal.py
manta_manim_theme-1.0.1.dist-info/METADATA
manta_manim_theme-1.0.1.dist-info/WHEEL
manta_manim_theme-1.0.1.dist-info/entry_points.txt
manta_manim_theme-1.0.1.dist-info/RECORD
