Metadata-Version: 2.1
Name: manta-manim-theme
Version: 1.0.1
Summary: 
Author: Alexander Nasuta
Author-email: alexander.nasuta@ima.rwth-aachen.de
Requires-Python: >=3.10,<3.13
Classifier: Programming Language :: Python :: 3
Classifier: Programming Language :: Python :: 3.10
Classifier: Programming Language :: Python :: 3.11
Classifier: Programming Language :: Python :: 3.12
Requires-Dist: click (>=8.1.8,<9.0.0)
Requires-Dist: flask (>=3.1.0,<4.0.0)
Requires-Dist: jsonschema (>=4.23.0,<5.0.0)
Requires-Dist: manim (<0.19)
Requires-Dist: manim-code-blocks (>=1.0.13,<2.0.0)
Requires-Dist: manim-voiceover[azure,gtts] (>=0.3.7,<0.4.0)
Requires-Dist: matplotlib (>=3.8,<3.9)
Requires-Dist: numba (>=0.60.0,<0.61.0)
Requires-Dist: rich (>=13.8.0,<14.0.0)
Requires-Dist: segno (>=1.6.1,<2.0.0)
Requires-Dist: typer[all] (>=0.12.5,<0.13.0)
Requires-Dist: waitress (>=3.0.2,<4.0.0)
